[
  {
    "id": "lighting-root",
    "question": "What lighting do you want?",
    "description": "Choose a category to begin",
    "attributeIds": [],
    "nextNodeId": null,
    "allowCustomExtension": []
  },
  {
    "id": "lighting-intensity-root",
    "question": "Light intensity",
    "description": "Select light intensity",
    "attributeIds": [
      "lighting:intensity-very-bright",
      "lighting:intensity-bright",
      "lighting:intensity-strong",
      "lighting:intensity-intense",
      "lighting:intensity-high-intensity",
      "lighting:intensity-moderate",
      "lighting:intensity-balanced",
      "lighting:intensity-neutral",
      "lighting:intensity-soft",
      "lighting:intensity-gentle",
      "lighting:intensity-low",
      "lighting:intensity-dim",
      "lighting:intensity-very-dim",
      "lighting:intensity-subtle",
      "lighting:intensity-minimal",
      "lighting:intensity-faint",
      "lighting:intensity-harsh",
      "lighting:intensity-blinding",
      "lighting:intensity-muted",
      "lighting:intensity-ambient",
      "lighting:intensity-overexposed",
      "lighting:intensity-underexposed",
      "lighting:intensity-low-key",
      "lighting:intensity-high-key",
      "lighting:intensity-whisper-soft",
      "lighting:intensity-glowingly-dim",
      "lighting:intensity-muted-low",
      "lighting:intensity-bright-burst",
      "lighting:intensity-piercing",
      "lighting:intensity-dim-ambient",
      "lighting:intensity-soft-diffuse",
      "lighting:intensity-punchy",
      "lighting:intensity-feathered",
      "lighting:intensity-soft-spill"
    ],
    "nextNodeId": null,
    "allowCustomExtension": []
  },
  {
    "id": "lighting-quality-root",
    "question": "Light quality",
    "description": "Select light quality",
    "attributeIds": [
      "lighting:quality-soft",
      "lighting:quality-hard",
      "lighting:quality-diffused",
      "lighting:quality-direct",
      "lighting:quality-natural",
      "lighting:quality-artificial",
      "lighting:quality-warm",
      "lighting:quality-cool",
      "lighting:quality-neutral",
      "lighting:quality-dramatic",
      "lighting:quality-cinematic",
      "lighting:quality-moody",
      "lighting:quality-flat",
      "lighting:quality-contrast-rich",
      "lighting:quality-volumetric",
      "lighting:quality-directional",
      "lighting:quality-rim",
      "lighting:quality-backlight",
      "lighting:quality-fill",
      "lighting:quality-key",
      "lighting:quality-crisp",
      "lighting:quality-smooth",
      "lighting:quality-contrasty",
      "lighting:quality-hazy",
      "lighting:quality-dusty",
      "lighting:quality-clean",
      "lighting:quality-soft-shadow",
      "lighting:quality-hard-shadow",
      "lighting:quality-bloomy",
      "lighting:quality-velvety",
      "lighting:quality-silky",
      "lighting:quality-granular",
      "lighting:quality-misty",
      "lighting:quality-glossy",
      "lighting:quality-diffuse",
      "lighting:quality-specular",
      "lighting:quality-painterly",
      "lighting:quality-velour",
      "lighting:quality-sparkling"
    ],
    "nextNodeId": null,
    "allowCustomExtension": []
  },
  {
    "id": "lighting-direction-root",
    "question": "Light direction",
    "description": "Select light direction",
    "attributeIds": [
      "lighting:direction-front",
      "lighting:direction-back",
      "lighting:direction-side",
      "lighting:direction-top",
      "lighting:direction-bottom",
      "lighting:direction-left",
      "lighting:direction-right",
      "lighting:direction-three-quarter",
      "lighting:direction-rim",
      "lighting:direction-overhead",
      "lighting:direction-under",
      "lighting:direction-cross",
      "lighting:direction-split",
      "lighting:direction-butterfly",
      "lighting:direction-loop",
      "lighting:direction-broad",
      "lighting:direction-short",
      "lighting:direction-edge",
      "lighting:direction-diagonal",
      "lighting:direction-halo",
      "lighting:direction-backlit",
      "lighting:direction-silhouette",
      "lighting:direction-top-down",
      "lighting:direction-bottom-up",
      "lighting:direction-side-left",
      "lighting:direction-side-right",
      "lighting:direction-short-light",
      "lighting:direction-broad-light",
      "lighting:direction-kicker",
      "lighting:direction-uplight",
      "lighting:direction-underlight",
      "lighting:direction-edge-light"
    ],
    "nextNodeId": null,
    "allowCustomExtension": []
  },
  {
    "id": "lighting-style-root",
    "question": "Light style",
    "description": "Select light style",
    "attributeIds": [
      "lighting:style-cinematic",
      "lighting:style-studio",
      "lighting:style-natural",
      "lighting:style-dramatic",
      "lighting:style-moody",
      "lighting:style-high-key",
      "lighting:style-low-key",
      "lighting:style-soft-box",
      "lighting:style-rim",
      "lighting:style-backlit",
      "lighting:style-neon",
      "lighting:style-ambient",
      "lighting:style-volumetric",
      "lighting:style-chiaroscuro",
      "lighting:style-film-noir",
      "lighting:style-golden-hour",
      "lighting:style-blue-hour",
      "lighting:style-stage",
      "lighting:style-editorial",
      "lighting:style-experimental",
      "lighting:style-candle",
      "lighting:style-firelight",
      "lighting:style-lantern",
      "lighting:style-floodlight",
      "lighting:style-spotlight",
      "lighting:style-strobe",
      "lighting:style-led",
      "lighting:style-practical",
      "lighting:style-sodium-vapor",
      "lighting:style-mercury-vapor",
      "lighting:style-laser",
      "lighting:style-bioluminescent",
      "lighting:style-glowstick",
      "lighting:style-paper-lantern",
      "lighting:style-torchlight",
      "lighting:style-studio-flash",
      "lighting:style-window-light"
    ],
    "nextNodeId": null,
    "allowCustomExtension": []
  },
  {
    "id": "lighting-time-root",
    "question": "Time-based light",
    "description": "Select time-based lighting",
    "attributeIds": [
      "lighting:time-sunrise",
      "lighting:time-early-morning",
      "lighting:time-morning",
      "lighting:time-midday",
      "lighting:time-afternoon",
      "lighting:time-golden-hour",
      "lighting:time-late-afternoon",
      "lighting:time-sunset",
      "lighting:time-twilight",
      "lighting:time-blue-hour",
      "lighting:time-early-evening",
      "lighting:time-dusk",
      "lighting:time-night",
      "lighting:time-midnight",
      "lighting:time-moonlight",
      "lighting:time-starlight",
      "lighting:time-overcast",
      "lighting:time-storm",
      "lighting:time-winter",
      "lighting:time-summer",
      "lighting:time-dawn",
      "lighting:time-moonlit",
      "lighting:time-stormy",
      "lighting:time-foggy",
      "lighting:time-pre-dawn",
      "lighting:time-afterglow",
      "lighting:time-civil-dawn",
      "lighting:time-nautical-dawn",
      "lighting:time-astronomical-dawn",
      "lighting:time-civil-dusk",
      "lighting:time-nautical-dusk",
      "lighting:time-astronomical-dusk",
      "lighting:time-equinox",
      "lighting:time-solstice"
    ],
    "nextNodeId": null,
    "allowCustomExtension": []
  },
  {
    "id": "lighting-cinematic-root",
    "question": "Cinematic & dramatic",
    "description": "Select cinematic lighting styles",
    "attributeIds": [
      "lighting:cinematic-dramatic",
      "lighting:cinematic-low-key",
      "lighting:cinematic-high-contrast",
      "lighting:cinematic-film-noir",
      "lighting:cinematic-chiaroscuro",
      "lighting:cinematic-moody",
      "lighting:cinematic-dark-atmospheric",
      "lighting:cinematic-spotlight",
      "lighting:cinematic-rim-lit",
      "lighting:cinematic-backlit-silhouette",
      "lighting:cinematic-volumetric",
      "lighting:cinematic-hard-edge",
      "lighting:cinematic-directional-dramatic",
      "lighting:cinematic-shadow-heavy",
      "lighting:cinematic-edge-lit",
      "lighting:cinematic-high-drama",
      "lighting:cinematic-stage",
      "lighting:cinematic-gothic",
      "lighting:cinematic-suspenseful",
      "lighting:cinematic-epic",
      "lighting:cinematic-practical",
      "lighting:cinematic-bounce",
      "lighting:cinematic-fill",
      "lighting:cinematic-key",
      "lighting:cinematic-back",
      "lighting:cinematic-motivated",
      "lighting:cinematic-sodium",
      "lighting:cinematic-tungsten",
      "lighting:cinematic-cool",
      "lighting:cinematic-warm",
      "lighting:cinematic-negative-fill",
      "lighting:cinematic-book-light",
      "lighting:cinematic-screen-glow",
      "lighting:cinematic-projector-light",
      "lighting:cinematic-moonlight-key",
      "lighting:cinematic-streetlight-key",
      "lighting:cinematic-practical-bokeh",
      "lighting:cinematic-soft-kicker",
      "lighting:cinematic-top-silhouette",
      "lighting:cinematic-edge-kicker"
    ],
    "nextNodeId": null,
    "allowCustomExtension": []
  },
  {
    "id": "lighting-artifact-root",
    "question": "Lighting artifacts",
    "description": "Select artifacts to avoid (negative prompt)",
    "attributeIds": [
      "lighting:artifact-overexposed",
      "lighting:artifact-underexposed",
      "lighting:artifact-lens-flare",
      "lighting:artifact-light-leak",
      "lighting:artifact-glow",
      "lighting:artifact-halo",
      "lighting:artifact-bloom",
      "lighting:artifact-ghosting",
      "lighting:artifact-band",
      "lighting:artifact-flicker",
      "lighting:artifact-chromatic-fringe",
      "lighting:artifact-scatter",
      "lighting:artifact-banding",
      "lighting:artifact-flare-orb",
      "lighting:artifact-flare-streak",
      "lighting:artifact-color-bleed",
      "lighting:artifact-hot-spot",
      "lighting:artifact-iris-glare",
      "lighting:artifact-flare-ghost",
      "lighting:artifact-sensor-bloom",
      "lighting:artifact-edge-glow",
      "lighting:artifact-light-smear"
    ],
    "nextNodeId": null,
    "allowCustomExtension": []
  }
]